camera/__init__.py
camera/__version__.py
camera/utils.py
camera/capture/__init__.py
camera/capture/blackflycapture.py
camera/capture/cv2capture.py
camera/capture/cv2captureProc.py
camera/capture/gcapture.py
camera/capture/libcamcapture.py
camera/capture/nanocapture.py
camera/capture/picamera2capture.py
camera/capture/picamera2captureQt.py
camera/capture/picamera2core.py
camera/capture/picapture.py
camera/capture/rtpcapture.py
camera/capture/rtspcapture.py
camera/processor/__init__.py
camera/processor/bgflatprocessor.py
camera/processor/highpassprocessor.py
camera/processor/runningsumprocessor.py
camera/streamer/__init__.py
camera/streamer/avistorageserver.py
camera/streamer/h5storageserver.py
camera/streamer/mkvstorageserver.py
camera/streamer/rtpserver.py
camera/streamer/rtpserverProc.py
camera/streamer/rtspserver.py
camera/streamer/tiffstorageserver.py
camera_util-1.3.3.dist-info/licenses/LICENSE
camera_util-1.3.3.dist-info/METADATA
camera_util-1.3.3.dist-info/WHEEL
camera_util-1.3.3.dist-info/top_level.txt
camera_util-1.3.3.dist-info/RECORD
