Metadata-Version: 2.4
Name: camera-util
Version: 1.3.3
Summary: Python wrapper for USB, blackfly, Raspi, Jetson Nano cameras. Works on Windows, Raspian (inlc Bullseye), JetsonNano, MacOS
Home-page: https://github.com/uutzinger/camera
Author: Urs Utzinger
Author-email: uutzinger@gmail.com
License: MIT
Keywords: camera,driver,opencv,blackfly
Classifier: Development Status :: 4 - Beta
Classifier: Intended Audience :: Developers
Classifier: Topic :: Multimedia :: Video :: Capture
Classifier: License :: OSI Approved :: MIT License
License-File: LICENSE
Dynamic: author
Dynamic: author-email
Dynamic: classifier
Dynamic: description
Dynamic: description-content-type
Dynamic: home-page
Dynamic: keywords
Dynamic: license
Dynamic: license-file
Dynamic: summary
